{
  "packages": [
    {
      "maintainer": "chipKIT Community",
      "help": {
        "online": "http://chipkit.net/started/learn-basics/"
      },
      "websiteURL": "http://chipkit.net/",
      "platforms": [
        {
          "name": "chipKIT",
          "architecture": "pic32",
          "version": "1.0.1",
          "category": "pic32",
          "url": "https://github.com/chipKIT32/chipKIT-core/releases/download/v1.0.1/chipkit-core-16778039.master-0d3a6ce.zip",
          "archiveFileName": "chipkit-core-16778039.master-0d3a6ce.zip",
          "checksum": "SHA-256:63B503606657467FA0040EB629FFF1BF7A86DA84E4608A7469294CA209BD1E3D",
          "help": {
            "online": "http://chipkit.net/started/learn-basics/"
          },
          "boards": [
            {"name": "cerebot32mx4"},
            {"name": "cerebot32mx7"},
            {"name": "cerebot_mx3ck"},
            {"name": "chipkit_mx3"},
            {"name": "cerebot_mx3ck_512"},
            {"name": "cerebot_mx4ck"},
            {"name": "chipkit_pro_mx4"},
            {"name": "cerebot_mx7ck"},
            {"name": "chipkit_pro_mx7"},
            {"name": "chipkit_Pi"},
            {"name": "chipkit_Pi_USB_Serial"},
            {"name": "cmod"},
            {"name": "CUI32stem"},
            {"name": "ubw32_mx460"},
            {"name": "ubw32_mx795"},
            {"name": "cui32"},
            {"name": "usbono_pic32"},
            {"name": "chipkit_DP32"},
            {"name": "fubarino_mini_dev"},
            {"name": "fubarino_mini"},
            {"name": "fubarino_sd_seeed"},
            {"name": "fubarino_sd"},
            {"name": "Fubarino_SDZ"},
            {"name": "mega_pic32"},
            {"name": "mega_usb_pic32"},
            {"name": "Olimex_Pinguino32"},
            {"name": "picadillo_35t"},
            {"name": "quick240_usb_pic32"},
            {"name": "chipkit_uc32"},
            {"name": "uc32_pmod"},
            {"name": "uno_pic32"},
            {"name": "uno_pmod"},
            {"name": "chipkit_WF32"},
            {"name": "chipkit_WiFire"},
            {"name": "chipkit_WiFire_80MHz"},
            {"name": "OpenScope"},
            {"name": "openbci"}
          ],
          "toolsDependencies": [
            {
              "packager": "chipKIT",
              "version": "4.8.3-pic32gcc",
              "name": "pic32-tools"
            }, 
            {
              "packager": "chipKIT",
              "version": "v1.0.01-pic32gcc",
              "name": "pic32prog"
            }
          ],
          "size": "7486796"
        }
      ],
      "tools": [
        {
          "version": "4.8.3-pic32gcc",
          "name": "pic32-tools",
          "systems": [
            {
              "url": "https://github.com/chipKIT32/chipKIT-core/releases/download/v1.0.1/pic32-tools-chipKIT-cxx-master-win32-image_bps.zip",
              "checksum": "SHA-256:33CBF281F681CC878EC2D4B9AA76EB3EA60C89E4E94AD3C3933CACD7242CDD11",
              "host": "i686-mingw32",
              "archiveFileName": "pic32-tools-chipKIT-cxx-master-win32-image_bps.zip",
              "size": "187130873"
            }, 
            {
              "url": "https://github.com/chipKIT32/chipKIT-core/releases/download/v1.0.1/pic32-tools-chipKIT-cxx-master-Darwin-image.zip",
              "checksum": "SHA-256:A7318FB14C86417621154FA96B04EE297BB1AAC7DD44A7881EACA9C3B24A496F",
              "host": "i386-apple-darwin",
              "archiveFileName": "pic32-tools-chipKIT-cxx-master-Darwin-image.zip",
              "size": "105119396"
            }, 
            {
              "url": "https://github.com/chipKIT32/chipKIT-core/releases/download/v1.0.1/pic32-tools-chipKIT-cxx-master-Linux32-image.zip",
              "checksum": "SHA-256:3A7C1FC3FDAAB3BF0FF60DAEB51EEA8221E4071F13DF5C3176FADCF9AC2F110A",
              "host": "x86_64-linux-gnu",
              "archiveFileName": "pic32-tools-chipKIT-cxx-master-Linux32-image.zip",
              "size": "98961200"
            }, 
            {
              "url": "https://github.com/chipKIT32/chipKIT-core/releases/download/v1.0.1/pic32-tools-chipKIT-cxx-master-Linux32-image.zip",
              "checksum": "SHA-256:3A7C1FC3FDAAB3BF0FF60DAEB51EEA8221E4071F13DF5C3176FADCF9AC2F110A",
              "host": "i686-pc-linux-gnu",
              "archiveFileName": "pic32-tools-chipKIT-cxx-master-Linux32-image.zip",
              "size": "98961200"
            }, 
            {
              "url": "https://github.com/chipKIT32/chipKIT-core/releases/download/v1.0.1/pic32-tools-chipKIT-cxx-master-arm-linux-image.zip",
              "checksum": "SHA-256:AA0B155E60AE53872E55F8557A95C0F995A964BCE65A9EE9138FC9AD1EB81019",
              "host": "i686-arm-gnu",
              "archiveFileName": "pic32-tools-chipKIT-cxx-master-arm-linux-image.zip",
              "size": "102719933"
            }
          ]
        },
        {
          "name": "pic32prog",
          "version": "v1.0.01-pic32gcc",
          "systems": [
            {
              "host": "i386-apple-darwin11",
              "url": "https://github.com/chipKIT32/chipKIT-core/releases/download/v1.0.1/pic32prog-macosx.zip",
              "archiveFileName": "pic32prog-macosx.zip",
              "size": "153322",
              "checksum": "SHA-256:69A0CBA683582D7752AB05517597BB5F352AC0273F4594BE95B9B134FD6F948F"
            }, 
            {
              "host": "x86_64-linux-gnu",
              "url": "https://github.com/chipKIT32/chipKIT-core/releases/download/v1.0.1/pic32prog-linux64.zip",
              "archiveFileName": "pic32prog-linux64.zip",
              "size": "104302",
              "checksum": "SHA-256:E4C0482085B0C9AAE88134AC587010B326DA0F989C1F3AF8BCC5E02C971E48AC"
            }, 
            {
              "host": "i686-pc-linux-gnu", 
              "url": "https://github.com/chipKIT32/chipKIT-core/releases/download/v1.0.1/pic32prog-linux32.zip",
              "archiveFileName": "pic32prog-linux32.zip",
              "size": "111157",
              "checksum": "SHA-256:3C19482EB6634F8BF0272A7B9786319F4E07B67FCF493842CD29E3086A171245"
            }, 
            {
              "host": "i686-mingw32",
              "url": "https://github.com/chipKIT32/chipKIT-core/releases/download/v1.0.1/pic32prog-windows.zip",
              "archiveFileName": "pic32prog-windows.zip",
              "size": "51434",
              "checksum": "SHA-256:C8F91AD8D29ED4EE2249B8EB9AB476F0B4CB54FF5F856C5953A1DC2EE1D51D19"
            }, 
            {
              "host": "i686-arm-gnu",
              "url": "https://github.com/chipKIT32/chipKIT-core/releases/download/v1.0.1/pic32prog-linuxarmhf.zip",
              "archiveFileName": "pic32prog-linuxarmhf.zip",
              "size": "240",
              "checksum": "SHA-256:75b39dab688fc3e030390ed1f131227e3e0ea0393c1e0e2348aa8f363eb9eea5db7010c87b51a454b35345c273e46021ab9b5f885fca9cf71df10631168f8ab5"
            }
          ]
        }
      ],
      "email": "packages@chipkit.net",
      "name": "chipKIT"
    }
  ]
}
